khmernltk/__init__.py
khmernltk/pos_tag/__init__.py
khmernltk/pos_tag/features.py
khmernltk/pos_tag/sklearn_crf_pos_alt_0.9846.sav
khmernltk/sentence_tokenize/__init__.py
khmernltk/sentence_tokenize/features.py
khmernltk/utils/__init__.py
khmernltk/utils/constants.py
khmernltk/utils/data.py
khmernltk/utils/file_utils.py
khmernltk/utils/log_utils.py
khmernltk/word_tokenize/__init__.py
khmernltk/word_tokenize/features.py
khmernltk/word_tokenize/sklearn_crf_ner_10000.sav
khmer_nltk-1.6.dist-info/LICENSE
khmer_nltk-1.6.dist-info/METADATA
khmer_nltk-1.6.dist-info/WHEEL
khmer_nltk-1.6.dist-info/top_level.txt
khmer_nltk-1.6.dist-info/RECORD
