Metadata-Version: 2.1
Name: khmer-nltk
Version: 1.6
Summary: A Khmer language processing toolkit
Home-page: https://github.com/VietHoang1710/khmer-nltk
Author: Phan Viet Hoang
Author-email: phanviethoang1512@gmail.com
License: Apache License 2.0
Classifier: Programming Language :: Python :: 3
Classifier: Operating System :: OS Independent
Classifier: Intended Audience :: Developers
Classifier: Natural Language :: English
Requires-Python: >3.5
Provides-Extra: test
License-File: LICENSE
